{
	"configurations" : 
	[
		{
			"directories" : 
			[
				{
					"build" : ".",
					"hasInstallRule" : true,
					"jsonFile" : "directory-.-0146c2d98cbc9030bcaf.json",
					"minimumCMakeVersion" : 
					{
						"string" : "3.12"
					},
					"projectIndex" : 0,
					"source" : ".",
					"targetIndexes" : 
					[
						0,
						1,
						2,
						3,
						4
					]
				}
			],
			"name" : "",
			"projects" : 
			[
				{
					"directoryIndexes" : 
					[
						0
					],
					"name" : "cpp07_exercise",
					"targetIndexes" : 
					[
						0,
						1,
						2,
						3,
						4
					]
				}
			],
			"targets" : 
			[
				{
					"directoryIndex" : 0,
					"id" : "cpp07_exercise_uninstall::@6890427a1f51a3e7e1df",
					"jsonFile" : "target-cpp07_exercise_uninstall-9883cacd106ee66304ec.json",
					"name" : "cpp07_exercise_uninstall",
					"projectIndex" : 0
				},
				{
					"directoryIndex" : 0,
					"id" : "exer01_pub_sub::@6890427a1f51a3e7e1df",
					"jsonFile" : "target-exer01_pub_sub-ab4e7dabac995f294823.json",
					"name" : "exer01_pub_sub",
					"projectIndex" : 0
				},
				{
					"directoryIndex" : 0,
					"id" : "exer02_server::@6890427a1f51a3e7e1df",
					"jsonFile" : "target-exer02_server-8d95fde30be7b61fec17.json",
					"name" : "exer02_server",
					"projectIndex" : 0
				},
				{
					"directoryIndex" : 0,
					"id" : "exer03_client::@6890427a1f51a3e7e1df",
					"jsonFile" : "target-exer03_client-767b294a0c86bcc045b0.json",
					"name" : "exer03_client",
					"projectIndex" : 0
				},
				{
					"directoryIndex" : 0,
					"id" : "uninstall::@6890427a1f51a3e7e1df",
					"jsonFile" : "target-uninstall-0305247cbd09dc30a373.json",
					"name" : "uninstall",
					"projectIndex" : 0
				}
			]
		}
	],
	"kind" : "codemodel",
	"paths" : 
	{
		"build" : "/home/lrm/ws01_plumbing/build/cpp07_exercise",
		"source" : "/home/lrm/ws01_plumbing/src/cpp07_exercise"
	},
	"version" : 
	{
		"major" : 2,
		"minor" : 3
	}
}
